pykinect_azure/__init__.py
pykinect_azure/pykinect.py
pykinect_azure/k4a/__init__.py
pykinect_azure/k4a/_k4a.py
pykinect_azure/k4a/_k4atypes.py
pykinect_azure/k4a/calibration.py
pykinect_azure/k4a/capture.py
pykinect_azure/k4a/configuration.py
pykinect_azure/k4a/device.py
pykinect_azure/k4a/image.py
pykinect_azure/k4a/imu_sample.py
pykinect_azure/k4a/transformation.py
pykinect_azure/k4abt/__init__.py
pykinect_azure/k4abt/_k4abt.py
pykinect_azure/k4abt/_k4abtTypes.py
pykinect_azure/k4abt/body.py
pykinect_azure/k4abt/body2d.py
pykinect_azure/k4abt/frame.py
pykinect_azure/k4abt/joint.py
pykinect_azure/k4abt/joint2d.py
pykinect_azure/k4abt/tracker.py
pykinect_azure/k4arecord/__init__.py
pykinect_azure/k4arecord/_k4arecord.py
pykinect_azure/k4arecord/_k4arecordTypes.py
pykinect_azure/k4arecord/datablock.py
pykinect_azure/k4arecord/playback.py
pykinect_azure/k4arecord/record.py
pykinect_azure/k4arecord/record_configuration.py
pykinect_azure/utils/__init__.py
pykinect_azure/utils/postProcessing.py
pykinect_azure/utils/utils.py
pykinect_azure-0.0.4.dist-info/METADATA
pykinect_azure-0.0.4.dist-info/WHEEL
pykinect_azure-0.0.4.dist-info/top_level.txt
pykinect_azure-0.0.4.dist-info/RECORD
