Metadata-Version: 2.1
Name: pykinect-azure
Version: 0.0.4
Summary: Python library to run Kinect Azure DK SDK functions
Home-page: https://github.com/ibaiGorordo/pyKinectAzure
Author: Ibai Gorordo
License: MIT
Requires-Dist: numpy
Requires-Dist: opencv-python
